radarreader/__init__.py
radarreader/radar.py
radarreader/test_radar.py
radarreader_omarimran2000-0.1.2.data/data/xethru_datafloat_20190614_141837.dat/xethru_datafloat_20190614_141837.dat
radarreader_omarimran2000-0.1.2.dist-info/LICENSE
radarreader_omarimran2000-0.1.2.dist-info/METADATA
radarreader_omarimran2000-0.1.2.dist-info/WHEEL
radarreader_omarimran2000-0.1.2.dist-info/top_level.txt
radarreader_omarimran2000-0.1.2.dist-info/RECORD
